<?xml version="1.0" encoding="ISO-8859-1"?>
<report xsi:noNamespaceSchemaLocation="report.xsd" xmlns:xsi="http://www.w3.org/2001/XMLSchema-instance">
	<title>ThreatExpert Report</title>
	<subreports>
		<subreport>
			<submission_summary>
				<submission_details>
					<submission_received>
						<day>7</day>
						<month>6</month>
						<year>2013</year>
						<hour>19</hour>
						<minute>21</minute>
						<second>43</second>
					</submission_received>
					<processing_time>
						<hours>0</hours>
						<minutes>24</minutes>
						<seconds>8</seconds>
					</processing_time>
					<sample_info_collection>
						<sample_info>
							<md5>6D778E0F95447E6546553EEEA709D03C</md5>
							<sha1>811A005CF787C6CCBE0D9F1C36C1D49A9CB71FD1</sha1>
							<filesize>389120</filesize>
							<alias_nav></alias_nav>
							<alias_kav></alias_kav>
							<alias_nai></alias_nai>
							<alias_trend></alias_trend>
							<alias_pctools></alias_pctools>
							<alias_sophos></alias_sophos>
							<alias_microsoft></alias_microsoft>
							<alias_ikarus></alias_ikarus>
							<alias_ahnlab></alias_ahnlab>
							<packer></packer>
						</sample_info>
					</sample_info_collection>
				</submission_details>
			</submission_summary>
			<technical_details>
			</technical_details>
		</subreport>
	</subreports>
</report>
